devqubit/__init__.py
devqubit/adapters.py
devqubit/bundle.py
devqubit/ci.py
devqubit/cli.py
devqubit/compare.py
devqubit/config.py
devqubit/errors.py
devqubit/py.typed
devqubit/runs.py
devqubit/storage.py
devqubit/uec.py
devqubit/ui.py
devqubit-0.1.10.dist-info/METADATA
devqubit-0.1.10.dist-info/WHEEL
devqubit-0.1.10.dist-info/entry_points.txt
devqubit-0.1.10.dist-info/licenses/LICENSE
devqubit-0.1.10.dist-info/RECORD
