Metadata-Version: 2.4
Name: devqubit
Version: 0.1.10
Summary: Quantum experiment tracking library
Project-URL: Homepage, https://devqubit.com
Project-URL: Repository, https://github.com/devqubit-labs/devqubit
Project-URL: Issues, https://github.com/devqubit-labs/devqubit/issues
Project-URL: Documentation, https://devqubit.readthedocs.io
Author: devqubit
License-Expression: Apache-2.0
License-File: LICENSE
Keywords: experiment-tracking,quantum
Classifier: Development Status :: 3 - Alpha
Classifier: Intended Audience :: Developers
Classifier: License :: OSI Approved :: Apache Software License
Classifier: Operating System :: OS Independent
Classifier: Programming Language :: Python :: 3
Classifier: Programming Language :: Python :: 3 :: Only
Classifier: Programming Language :: Python :: 3.11
Classifier: Programming Language :: Python :: 3.12
Classifier: Programming Language :: Python :: 3.13
Classifier: Topic :: Scientific/Engineering
Requires-Python: <3.14,>=3.11
Requires-Dist: devqubit-engine<0.2.0,>=0.1.10
Provides-Extra: all
Requires-Dist: devqubit-braket<0.2.0,>=0.1.10; extra == 'all'
Requires-Dist: devqubit-cirq<0.2.0,>=0.1.10; extra == 'all'
Requires-Dist: devqubit-pennylane<0.2.0,>=0.1.10; extra == 'all'
Requires-Dist: devqubit-qiskit-runtime<0.2.0,>=0.1.10; extra == 'all'
Requires-Dist: devqubit-qiskit<0.2.0,>=0.1.10; extra == 'all'
Provides-Extra: braket
Requires-Dist: devqubit-braket<0.2.0,>=0.1.10; extra == 'braket'
Provides-Extra: cirq
Requires-Dist: devqubit-cirq<0.2.0,>=0.1.10; extra == 'cirq'
Provides-Extra: gcs
Requires-Dist: devqubit-engine[gcs]<0.2.0,>=0.1.10; extra == 'gcs'
Provides-Extra: pennylane
Requires-Dist: devqubit-pennylane<0.2.0,>=0.1.10; extra == 'pennylane'
Provides-Extra: qiskit
Requires-Dist: devqubit-qiskit<0.2.0,>=0.1.10; extra == 'qiskit'
Provides-Extra: qiskit-runtime
Requires-Dist: devqubit-qiskit-runtime<0.2.0,>=0.1.10; extra == 'qiskit-runtime'
Provides-Extra: s3
Requires-Dist: devqubit-engine[s3]<0.2.0,>=0.1.10; extra == 's3'
Provides-Extra: ui
Requires-Dist: devqubit-ui<0.2.0,>=0.1.10; extra == 'ui'
